curator/__init__.py
curator/cli.py
curator/user_cfg.yaml
curator/utils.py
curator/configs/__init__.py
curator/configs/label.yaml
curator/configs/select.yaml
curator/configs/simulate.yaml
curator/configs/train.yaml
curator/configs/annotator/vasp.yaml
curator/configs/annotator/vasp_annotator.yaml
curator/configs/annotator/calc_params/vasp_params.yaml
curator/configs/annotator/calculator/gpaw.yaml
curator/configs/annotator/calculator/vasp.yaml
curator/configs/data/custom.yaml
curator/configs/model/nnp.yaml
curator/configs/model/repr_params/mace_params.yaml
curator/configs/model/repr_params/nequip_params.yaml
curator/configs/model/repr_params/painn_params.yaml
curator/configs/model/representation/mace.yaml
curator/configs/model/representation/nequip.yaml
curator/configs/model/representation/painn.yaml
curator/configs/simulator/md.yaml
curator/configs/simulator/md_meta.yaml
curator/configs/simulator/neb.yaml
curator/configs/simulator/dynamics/andersen.yaml
curator/configs/simulator/dynamics/langevin.yaml
curator/configs/simulator/dynamics/verlet.yaml
curator/configs/simulator/logger/md_logger.yaml
curator/configs/simulator/uncertainty/ensemble.yaml
curator/configs/task/default_task.yaml
curator/configs/task/optimizer/adam.yaml
curator/configs/task/optimizer/adam_amsgrad.yaml
curator/configs/task/outputs/energy_force.yaml
curator/configs/task/outputs/energy_force_per_species.yaml
curator/configs/task/outputs/energy_force_stress.yaml
curator/configs/task/outputs/energy_force_stress_per_species.yaml
curator/configs/task/scheduler/exponential.yaml
curator/configs/task/scheduler/reduce_on_plateau.yaml
curator/configs/trainer/default_trainer.yaml
curator/configs/trainer/logger/csv.yaml
curator/configs/trainer/logger/wandb.yaml
curator/configs/uncertainty/ensemble.yaml
curator/configs/uncertainty/mc_dropout.yaml
curator/data/__init__.py
curator/data/_data_reader.py
curator/data/_neighborlist.py
curator/data/_transform.py
curator/data/_type_mapper.py
curator/data/datamodule.py
curator_torch-1.1.1.dist-info/METADATA
curator_torch-1.1.1.dist-info/WHEEL
curator_torch-1.1.1.dist-info/top_level.txt
curator_torch-1.1.1.dist-info/RECORD
