Metadata-Version: 2.1
Name: curator-torch
Version: 1.1.1
Summary: Library for implementation of message passing neural networks in Pytorch
Home-page: https://github.com/dtu-energy/curator.git
Author: xinyang
Author-email: xinyang@dtu.dk
Requires-Dist: myqueue
Requires-Dist: torch>=1.10
Requires-Dist: ase
Requires-Dist: asap3
Requires-Dist: e3nn
Requires-Dist: torch-ema>=0.3.0
Requires-Dist: toml
Requires-Dist: numpy
Requires-Dist: hydra-core>=1.2
Requires-Dist: wandb
Requires-Dist: lightning
